MANIFEST.in
README.rst
setup.py
pyravendb_embedded/__init__.py
pyravendb_embedded/database_options.py
pyravendb_embedded/embedded_server.py
pyravendb_embedded/ravenserver_runner.py
pyravendb_embedded/server_options.py
pyravendb_embedded.egg-info/PKG-INFO
pyravendb_embedded.egg-info/SOURCES.txt
pyravendb_embedded.egg-info/dependency_links.txt
pyravendb_embedded.egg-info/not-zip-safe
pyravendb_embedded.egg-info/requires.txt
pyravendb_embedded.egg-info/top_level.txt
pyravendb_embedded/RavenDBServer/BouncyCastle.Crypto.dll
pyravendb_embedded/RavenDBServer/CsvHelper.dll
pyravendb_embedded/RavenDBServer/DasMulli.Win32.ServiceUtils.dll
pyravendb_embedded/RavenDBServer/Esprima.dll
pyravendb_embedded/RavenDBServer/GeoAPI.dll
pyravendb_embedded/RavenDBServer/Google.Protobuf.dll
pyravendb_embedded/RavenDBServer/Jint.dll
pyravendb_embedded/RavenDBServer/Lambda2Js.Signed.dll
pyravendb_embedded/RavenDBServer/Lucene.Net.Contrib.Spatial.NTS.dll
pyravendb_embedded/RavenDBServer/Lucene.Net.dll
pyravendb_embedded/RavenDBServer/Microsoft.AspNetCore.Connections.Abstractions.dll
pyravendb_embedded/RavenDBServer/Microsoft.AspNetCore.Hosting.Abstractions.dll
pyravendb_embedded/RavenDBServer/Microsoft.AspNetCore.Hosting.Server.Abstractions.dll
pyravendb_embedded/RavenDBServer/Microsoft.AspNetCore.Hosting.dll
pyravendb_embedded/RavenDBServer/Microsoft.AspNetCore.Http.Abstractions.dll
pyravendb_embedded/RavenDBServer/Microsoft.AspNetCore.Http.Extensions.dll
pyravendb_embedded/RavenDBServer/Microsoft.AspNetCore.Http.Features.dll
pyravendb_embedded/RavenDBServer/Microsoft.AspNetCore.Http.dll
pyravendb_embedded/RavenDBServer/Microsoft.AspNetCore.ResponseCompression.dll
pyravendb_embedded/RavenDBServer/Microsoft.AspNetCore.Server.Kestrel.Core.dll
pyravendb_embedded/RavenDBServer/Microsoft.AspNetCore.Server.Kestrel.Https.dll
pyravendb_embedded/RavenDBServer/Microsoft.AspNetCore.Server.Kestrel.Transport.Abstractions.dll
pyravendb_embedded/RavenDBServer/Microsoft.AspNetCore.Server.Kestrel.Transport.Libuv.dll
pyravendb_embedded/RavenDBServer/Microsoft.AspNetCore.Server.Kestrel.Transport.Sockets.dll
pyravendb_embedded/RavenDBServer/Microsoft.AspNetCore.Server.Kestrel.dll
pyravendb_embedded/RavenDBServer/Microsoft.AspNetCore.WebSockets.dll
