Metadata-Version: 1.0
Name: pyravendb-embedded
Version: 4.1.1.4
Summary: RavenDB Embedded library to run ravendb in embedded way
Home-page: https://github.com/ravendb/ravendb-python-embedded
Author: RavenDB
Author-email: support@ravendb.net
License: Custom EULA
Keywords: pyravendb embedded database nosql doc db
Platform: UNKNOWN
